pyaltername/__init__.py
pyaltername/__version__.py
pyaltername/app.py
pyaltername-0.0.1.dist-info/LICENSE
pyaltername-0.0.1.dist-info/METADATA
pyaltername-0.0.1.dist-info/WHEEL
pyaltername-0.0.1.dist-info/top_level.txt
pyaltername-0.0.1.dist-info/RECORD
