Metadata-Version: 2.1
Name: pyaltername
Version: 0.0.1
Summary: A small python package to name, rename files without conflicts
Home-page: https://github.com/Mgregchi/pyaltername/
Author: Micahel Amadi
Author-email: mgregchi@gmail.com
License: UNKNOWN
Platform: UNKNOWN
Classifier: Intended Audience :: Developers
Classifier: Programming Language :: Python :: 3
Classifier: License :: OSI Approved :: Apache Software License
Classifier: Natural Language :: English
Requires-Python: >=3.6
